JiankangZhidao/Dockerfile
JiankangZhidao/README.md
JiankangZhidao/__init__.py
JiankangZhidao/__main__.py
JiankangZhidao/file.epub
JiankangZhidao/index.html
JiankangZhidao/css/__init__.py
JiankangZhidao/css/annotations.css
JiankangZhidao/css/main.css
JiankangZhidao/css/normalize.css
JiankangZhidao/css/popup.css
JiankangZhidao/font/__init__.py
JiankangZhidao/font/fontello.eot
JiankangZhidao/font/fontello.svg
JiankangZhidao/font/fontello.ttf
JiankangZhidao/font/fontello.woff
JiankangZhidao/img/__init__.py
JiankangZhidao/img/annotator-glyph-sprite.png
JiankangZhidao/img/annotator-icon-sprite.png
JiankangZhidao/img/apple-touch-icon.png
JiankangZhidao/img/cancelfullscreen.png
JiankangZhidao/img/close.png
JiankangZhidao/img/fullscreen.png
JiankangZhidao/img/loader.gif
JiankangZhidao/img/menu-icon.png
JiankangZhidao/img/save.png
JiankangZhidao/img/saved.png
JiankangZhidao/img/settings-s.png
JiankangZhidao/img/settings.png
JiankangZhidao/img/star.png
JiankangZhidao/js/__init__.py
JiankangZhidao/js/epub.js
JiankangZhidao/js/epub.min.js
JiankangZhidao/js/epub.min.map
JiankangZhidao/js/hooks.min.js
JiankangZhidao/js/hooks.min.map
JiankangZhidao/js/reader.js
JiankangZhidao/js/reader.js.map
JiankangZhidao/js/reader.min.js
JiankangZhidao/js/reader.min.map
JiankangZhidao/js/hooks/__init__.py
JiankangZhidao/js/hooks/extensions/__init__.py
JiankangZhidao/js/hooks/extensions/highlight.js
JiankangZhidao/js/libs/__init__.py
JiankangZhidao/js/libs/jquery.min.js
JiankangZhidao/js/libs/localforage.min.js
JiankangZhidao/js/libs/screenfull.js
JiankangZhidao/js/libs/screenfull.min.js
JiankangZhidao/js/libs/zip.min.js
JiankangZhidao/js/plugins/__init__.py
JiankangZhidao/js/plugins/hypothesis.js
JiankangZhidao/js/plugins/search.js
jiankang_zhidao-2022.10.9.1.dist-info/METADATA
jiankang_zhidao-2022.10.9.1.dist-info/WHEEL
jiankang_zhidao-2022.10.9.1.dist-info/entry_points.txt
jiankang_zhidao-2022.10.9.1.dist-info/top_level.txt
jiankang_zhidao-2022.10.9.1.dist-info/RECORD
